Metadata-Version: 2.1
Name: LesionMapUCSF
Version: 1.0.0
Summary: Segmentation, normalization, visualization of imaging segments
Project-URL: Homepage, https://github.com/mnegussie/LesionMap
Project-URL: Bug Tracker, https://github.com/mnegussie/LesionMap/issues
Author-email: Mikias Negussie <mikias.negussie@ucsf.edu>
Classifier: License :: OSI Approved :: MIT License
Classifier: Operating System :: OS Independent
Classifier: Programming Language :: Python :: 3
Requires-Python: >=3.7
